cmupy/__init__.py
cmupy/cli.py
cmupy/core.py
cmupy-0.1.0.dist-info/METADATA
cmupy-0.1.0.dist-info/WHEEL
cmupy-0.1.0.dist-info/entry_points.txt
cmupy-0.1.0.dist-info/licenses/LICENSE
cmupy-0.1.0.dist-info/RECORD
