Metadata-Version: 2.4
Name: cmupy
Version: 0.1.0
Summary: A Python package for computational utilities
Project-URL: Homepage, https://github.com/sanziolopes-cmu/cmupy
Project-URL: Documentation, https://github.com/sanziolopes-cmu/cmupy#readme
Project-URL: Repository, https://github.com/sanziolopes-cmu/cmupy
Project-URL: Issues, https://github.com/sanziolopes-cmu/cmupy/issues
Author-email: SanzioDinelli <sanzio.magalhae@gmail.com>
License:                     GNU GENERAL PUBLIC LICENSE
License-File: LICENSE
Keywords: cli,computational,ruff,utilities
Classifier: Development Status :: 3 - Alpha
Classifier: Intended Audience :: Developers
Classifier: Intended Audience :: Education
Classifier: Intended Audience :: Science/Research
Classifier: License :: OSI Approved :: GNU General Public License v3 (GPLv3)
Classifier: Programming Language :: Python :: 3.12
Classifier: Topic :: Scientific/Engineering
Classifier: Topic :: Utilities
Requires-Python: >=3.12
Provides-Extra: test
Requires-Dist: pytest-cov>=4.0.0; extra == 'test'
Requires-Dist: pytest>=7.0.0; extra == 'test'
